burette.py
burette-0.1.data/scripts/burette.py
burette-0.1.dist-info/LICENSE
burette-0.1.dist-info/METADATA
burette-0.1.dist-info/WHEEL
burette-0.1.dist-info/top_level.txt
burette-0.1.dist-info/RECORD
